gregpilottui/.gitignore
gregpilottui/__about__.py
gregpilottui/__init__.py
gregpilottui/api.py
gregpilottui/app.py
gregpilottui/config.py
gregpilottui/craftpopup.py
gregpilottui/gp.tcss
gregpilottui/gregpilottui.py
gregpilottui/initpopup.py
gregpilottui/invtable.py
gregpilottui/requirements.txt
gregpilottui-0.1.4.dist-info/METADATA
gregpilottui-0.1.4.dist-info/WHEEL
gregpilottui-0.1.4.dist-info/entry_points.txt
gregpilottui-0.1.4.dist-info/licenses/LICENSE.txt
gregpilottui-0.1.4.dist-info/RECORD
