Metadata-Version: 2.4
Name: gregpilottui
Version: 0.1.4
Summary: A terminal UI for the GregPilot control server
Project-URL: Documentation, https://github.com/Alex Kendrick/gregpilottui#readme
Project-URL: Issues, https://github.com/Alex Kendrick/gregpilottui/issues
Project-URL: Source, https://github.com/Alex Kendrick/gregpilottui
Author-email: Alex Kendrick <alex@alex-kendrick.com>
License-Expression: MIT
License-File: LICENSE.txt
Classifier: Development Status :: 4 - Beta
Classifier: Programming Language :: Python
Classifier: Programming Language :: Python :: 3.8
Classifier: Programming Language :: Python :: 3.9
Classifier: Programming Language :: Python :: 3.10
Classifier: Programming Language :: Python :: 3.11
Classifier: Programming Language :: Python :: 3.12
Classifier: Programming Language :: Python :: Implementation :: CPython
Classifier: Programming Language :: Python :: Implementation :: PyPy
Requires-Python: >=3.8
Requires-Dist: aiohappyeyeballs==2.6.1
Requires-Dist: aiohttp-jinja2==1.6
Requires-Dist: aiohttp==3.13.2
Requires-Dist: aiosignal==1.4.0
Requires-Dist: attrs==25.4.0
Requires-Dist: certifi==2025.11.12
Requires-Dist: charset-normalizer==3.4.4
Requires-Dist: click==8.3.1
Requires-Dist: frozenlist==1.8.0
Requires-Dist: idna==3.11
Requires-Dist: jinja2==3.1.6
Requires-Dist: linkify-it-py==2.0.3
Requires-Dist: markdown-it-py==4.0.0
Requires-Dist: markupsafe==3.0.3
Requires-Dist: mdit-py-plugins==0.5.0
Requires-Dist: mdurl==0.1.2
Requires-Dist: msgpack==1.1.2
Requires-Dist: multidict==6.7.0
Requires-Dist: platformdirs==4.5.1
Requires-Dist: propcache==0.4.1
Requires-Dist: pygments==2.19.2
Requires-Dist: requests==2.32.5
Requires-Dist: rich==14.2.0
Requires-Dist: textual-dev==1.8.0
Requires-Dist: textual-serve==1.1.3
Requires-Dist: textual==6.9.0
Requires-Dist: typing-extensions==4.15.0
Requires-Dist: uc-micro-py==1.0.3
Requires-Dist: urllib3==2.6.2
Requires-Dist: yarl==1.22.0
